com/__init__.py
com/yootk/__init__.py
com/yootk/info/__init__.py
com/yootk/info/message.py
kudejian_message-1.1.2.dist-info/METADATA
kudejian_message-1.1.2.dist-info/WHEEL
kudejian_message-1.1.2.dist-info/top_level.txt
kudejian_message-1.1.2.dist-info/RECORD
